calgebra/__init__.py
calgebra/cache.py
calgebra/core.py
calgebra/dataframe.py
calgebra/gcsa.py
calgebra/ical.py
calgebra/interval.py
calgebra/metrics.py
calgebra/properties.py
calgebra/py.typed
calgebra/recurrence.py
calgebra/transform.py
calgebra/util.py
calgebra/docs/API.md
calgebra/docs/GCSA.md
calgebra/docs/QUICK-START.md
calgebra/docs/README.md
calgebra/docs/TUTORIAL.md
calgebra/mutable/__init__.py
calgebra/mutable/memory.py
calgebra-0.10.6.dist-info/licenses/LICENSE
calgebra-0.10.6.dist-info/METADATA
calgebra-0.10.6.dist-info/WHEEL
calgebra-0.10.6.dist-info/top_level.txt
calgebra-0.10.6.dist-info/RECORD
