Metadata-Version: 2.4
Name: calgebra
Version: 0.10.6
Summary: A tiny DSL for calendar interval algebra - compose, filter, and query time ranges using set operations.
Author: ashenfad
License: MIT
Project-URL: Homepage, https://github.com/ashenfad/calgebra
Project-URL: Bug Tracker, https://github.com/ashenfad/calgebra/issues
Project-URL: Documentation, https://github.com/ashenfad/calgebra#readme
Project-URL: Source, https://github.com/ashenfad/calgebra
Keywords: calendar,scheduling,intervals,time,algebra,dsl
Classifier: Development Status :: 4 - Beta
Classifier: Intended Audience :: Developers
Classifier: Topic :: Software Development :: Libraries :: Python Modules
Classifier: Topic :: Office/Business :: Scheduling
Classifier: Programming Language :: Python :: 3
Classifier: Programming Language :: Python :: 3.10
Classifier: Programming Language :: Python :: 3.11
Classifier: Programming Language :: Python :: 3.12
Classifier: Programming Language :: Python :: 3.13
Classifier: Programming Language :: Python :: 3.14
Classifier: License :: OSI Approved :: MIT License
Classifier: Operating System :: OS Independent
Classifier: Typing :: Typed
Requires-Python: >=3.10
License-File: LICENSE
Requires-Dist: python-dateutil>=2.8.0
Requires-Dist: typing-extensions>=4.0.0
Requires-Dist: sortedcontainers>=2.4.0
Provides-Extra: dev
Requires-Dist: ruff; extra == "dev"
Requires-Dist: pre-commit; extra == "dev"
Requires-Dist: uv; extra == "dev"
Requires-Dist: pytest; extra == "dev"
Requires-Dist: gcsa>=2.6.0; extra == "dev"
Requires-Dist: icalendar>=6.1.0; extra == "dev"
Requires-Dist: pandas>=2.0; extra == "dev"
Provides-Extra: google-calendar
Requires-Dist: gcsa>=2.6.0; extra == "google-calendar"
Provides-Extra: ical
Requires-Dist: icalendar>=6.1.0; extra == "ical"
Provides-Extra: pandas
Requires-Dist: pandas>=2.0; extra == "pandas"
Dynamic: license-file
